timona/__init__.py
timona/__main__.py
timona/__version__.py
timona/config.py
timona/helm.py
timona/main.py
timona/releases.py
timona/template/__init__.py
timona/template/module_jinja2.py
timona-1.0.2.dist-info/METADATA
timona-1.0.2.dist-info/WHEEL
timona-1.0.2.dist-info/entry_points.txt
timona-1.0.2.dist-info/licenses/LICENSE
timona-1.0.2.dist-info/RECORD
