Metadata-Version: 2.4
Name: timona
Version: 1.0.2
Summary: Tool to automate Helm deployments
License-File: LICENSE
Author: mihaiush
Author-email: mihaiush@gmail.com
Requires-Python: >=3.7,<4.0
Classifier: Programming Language :: Python :: 3
Classifier: Programming Language :: Python :: 3.7
Classifier: Programming Language :: Python :: 3.8
Classifier: Programming Language :: Python :: 3.9
Classifier: Programming Language :: Python :: 3.10
Classifier: Programming Language :: Python :: 3.11
Classifier: Programming Language :: Python :: 3.12
Classifier: Programming Language :: Python :: 3.13
Classifier: Programming Language :: Python :: 3.14
Requires-Dist: deepmerge
Requires-Dist: jinja2
Requires-Dist: pyyaml
Requires-Dist: requests
Project-URL: Homepage, https://github.com/mihaiush/timona
